{
  "Color": {
    "red-50": {
      "$extensions": {
        "com.figma.hiddenFromPublishing": false
      },
      "$type": "color",
      "$value": "#ffebea"
    },
    "red-100": {
      "$extensions": {
        "com.figma.hiddenFromPublishing": false
      },
      "$type": "color",
      "$value": "#ffc2bf"
    },
    "red-200": {
      "$extensions": {
        "com.figma.hiddenFromPublishing": false
      },
      "$type": "color",
      "$value": "#ffa5a0"
    },
    "red-300": {
      "$extensions": {
        "com.figma.hiddenFromPublishing": false
      },
      "$type": "color",
      "$value": "#ff7c74"
    },
    "red-400": {
      "$extensions": {
        "com.figma.hiddenFromPublishing": false
      },
      "$type": "color",
      "$value": "#ff6259"
    },
    "red-500": {
      "$extensions": {
        "com.figma.hiddenFromPublishing": false
      },
      "$type": "color",
      "$value": "#ff3b30"
    },
    "red-600": {
      "$extensions": {
        "com.figma.hiddenFromPublishing": false
      },
      "$type": "color",
      "$value": "#e8362c"
    },
    "red-700": {
      "$extensions": {
        "com.figma.hiddenFromPublishing": false
      },
      "$type": "color",
      "$value": "#b52a22"
    },
    "red-800": {
      "$extensions": {
        "com.figma.hiddenFromPublishing": false
      },
      "$type": "color",
      "$value": "#8c201a"
    },
    "red-900": {
      "$extensions": {
        "com.figma.hiddenFromPublishing": false
      },
      "$type": "color",
      "$value": "#6b1914"
    },
    "orange-50": {
      "$extensions": {
        "com.figma.hiddenFromPublishing": false
      },
      "$type": "color",
      "$value": "#fff4e6"
    },
    "orange-100": {
      "$extensions": {
        "com.figma.hiddenFromPublishing": false
      },
      "$type": "color",
      "$value": "#ffdeb0"
    },
    "orange-200": {
      "$extensions": {
        "com.figma.hiddenFromPublishing": false
      },
      "$type": "color",
      "$value": "#ffce8a"
    },
    "orange-300": {
      "$extensions": {
        "com.figma.hiddenFromPublishing": false
      },
      "$type": "color",
      "$value": "#ffb854"
    },
    "orange-400": {
      "$extensions": {
        "com.figma.hiddenFromPublishing": false
      },
      "$type": "color",
      "$value": "#ffaa33"
    },
    "orange-500": {
      "$extensions": {
        "com.figma.hiddenFromPublishing": false
      },
      "$type": "color",
      "$value": "#ff9500"
    },
    "orange-600": {
      "$extensions": {
        "com.figma.hiddenFromPublishing": false
      },
      "$type": "color",
      "$value": "#e88800"
    },
    "orange-700": {
      "$extensions": {
        "com.figma.hiddenFromPublishing": false
      },
      "$type": "color",
      "$value": "#b56a00"
    },
    "orange-800": {
      "$extensions": {
        "com.figma.hiddenFromPublishing": false
      },
      "$type": "color",
      "$value": "#8c5200"
    },
    "orange-900": {
      "$extensions": {
        "com.figma.hiddenFromPublishing": false
      },
      "$type": "color",
      "$value": "#6b3f00"
    },
    "black": {
      "$extensions": {
        "com.figma.hiddenFromPublishing": false
      },
      "$type": "color",
      "$value": "#000000"
    },
    "black-a10": {
      "$extensions": {
        "com.figma.hiddenFromPublishing": false
      },
      "$type": "color",
      "$value": "#0000001a"
    },
    "black-a20": {
      "$extensions": {
        "com.figma.hiddenFromPublishing": false
      },
      "$type": "color",
      "$value": "#00000033"
    },
    "black-a30": {
      "$extensions": {
        "com.figma.hiddenFromPublishing": false
      },
      "$type": "color",
      "$value": "#0000004d"
    },
    "black-a40": {
      "$extensions": {
        "com.figma.hiddenFromPublishing": false
      },
      "$type": "color",
      "$value": "#00000066"
    },
    "black-a50": {
      "$extensions": {
        "com.figma.hiddenFromPublishing": false
      },
      "$type": "color",
      "$value": "#00000080"
    },
    "black-a60": {
      "$extensions": {
        "com.figma.hiddenFromPublishing": false
      },
      "$type": "color",
      "$value": "#00000099"
    },
    "black-a70": {
      "$extensions": {
        "com.figma.hiddenFromPublishing": false
      },
      "$type": "color",
      "$value": "#000000b3"
    },
    "black-a80": {
      "$extensions": {
        "com.figma.hiddenFromPublishing": false
      },
      "$type": "color",
      "$value": "#000000cc"
    },
    "black-a90": {
      "$extensions": {
        "com.figma.hiddenFromPublishing": false
      },
      "$type": "color",
      "$value": "#000000e6"
    },
    "white": {
      "$extensions": {
        "com.figma.hiddenFromPublishing": false
      },
      "$type": "color",
      "$value": "#ffffff"
    },
    "white-a10": {
      "$extensions": {
        "com.figma.hiddenFromPublishing": false
      },
      "$type": "color",
      "$value": "#ffffff1a"
    },
    "white-a20": {
      "$extensions": {
        "com.figma.hiddenFromPublishing": false
      },
      "$type": "color",
      "$value": "#ffffff33"
    },
    "white-a30": {
      "$extensions": {
        "com.figma.hiddenFromPublishing": false
      },
      "$type": "color",
      "$value": "#ffffff4d"
    },
    "white-a40": {
      "$extensions": {
        "com.figma.hiddenFromPublishing": false
      },
      "$type": "color",
      "$value": "#ffffff66"
    },
    "white-a50": {
      "$extensions": {
        "com.figma.hiddenFromPublishing": false
      },
      "$type": "color",
      "$value": "#ffffff80"
    },
    "white-a60": {
      "$extensions": {
        "com.figma.hiddenFromPublishing": false
      },
      "$type": "color",
      "$value": "#ffffff99"
    },
    "white-a70": {
      "$extensions": {
        "com.figma.hiddenFromPublishing": false
      },
      "$type": "color",
      "$value": "#ffffffb3"
    },
    "white-a80": {
      "$extensions": {
        "com.figma.hiddenFromPublishing": false
      },
      "$type": "color",
      "$value": "#ffffffcc"
    },
    "white-a90": {
      "$extensions": {
        "com.figma.hiddenFromPublishing": false
      },
      "$type": "color",
      "$value": "#ffffffe6"
    },
    "yellow-50": {
      "$extensions": {
        "com.figma.hiddenFromPublishing": false
      },
      "$type": "color",
      "$value": "#fffae6"
    },
    "yellow-100": {
      "$extensions": {
        "com.figma.hiddenFromPublishing": false
      },
      "$type": "color",
      "$value": "#ffefb0"
    },
    "yellow-200": {
      "$extensions": {
        "com.figma.hiddenFromPublishing": false
      },
      "$type": "color",
      "$value": "#ffe88a"
    },
    "yellow-300": {
      "$extensions": {
        "com.figma.hiddenFromPublishing": false
      },
      "$type": "color",
      "$value": "#ffdd54"
    },
    "yellow-400": {
      "$extensions": {
        "com.figma.hiddenFromPublishing": false
      },
      "$type": "color",
      "$value": "#ffd633"
    },
    "yellow-500": {
      "$extensions": {
        "com.figma.hiddenFromPublishing": false
      },
      "$type": "color",
      "$value": "#ffcc00"
    },
    "yellow-600": {
      "$extensions": {
        "com.figma.hiddenFromPublishing": false
      },
      "$type": "color",
      "$value": "#e8ba00"
    },
    "yellow-700": {
      "$extensions": {
        "com.figma.hiddenFromPublishing": false
      },
      "$type": "color",
      "$value": "#b59100"
    },
    "yellow-800": {
      "$extensions": {
        "com.figma.hiddenFromPublishing": false
      },
      "$type": "color",
      "$value": "#8c7000"
    },
    "yellow-900": {
      "$extensions": {
        "com.figma.hiddenFromPublishing": false
      },
      "$type": "color",
      "$value": "#6b5600"
    },
    "green-50": {
      "$extensions": {
        "com.figma.hiddenFromPublishing": false
      },
      "$type": "color",
      "$value": "#ebf9ee"
    },
    "green-100": {
      "$extensions": {
        "com.figma.hiddenFromPublishing": false
      },
      "$type": "color",
      "$value": "#c0eecc"
    },
    "green-200": {
      "$extensions": {
        "com.figma.hiddenFromPublishing": false
      },
      "$type": "color",
      "$value": "#a2e5b3"
    },
    "green-300": {
      "$extensions": {
        "com.figma.hiddenFromPublishing": false
      },
      "$type": "color",
      "$value": "#77d990"
    },
    "green-400": {
      "$extensions": {
        "com.figma.hiddenFromPublishing": false
      },
      "$type": "color",
      "$value": "#5dd27a"
    },
    "green-500": {
      "$extensions": {
        "com.figma.hiddenFromPublishing": false
      },
      "$type": "color",
      "$value": "#34c759"
    },
    "green-600": {
      "$extensions": {
        "com.figma.hiddenFromPublishing": false
      },
      "$type": "color",
      "$value": "#2fb551"
    },
    "green-700": {
      "$extensions": {
        "com.figma.hiddenFromPublishing": false
      },
      "$type": "color",
      "$value": "#258d3f"
    },
    "green-800": {
      "$extensions": {
        "com.figma.hiddenFromPublishing": false
      },
      "$type": "color",
      "$value": "#1d6d31"
    },
    "green-900": {
      "$extensions": {
        "com.figma.hiddenFromPublishing": false
      },
      "$type": "color",
      "$value": "#165425"
    },
    "mint-50": {
      "$extensions": {
        "com.figma.hiddenFromPublishing": false
      },
      "$type": "color",
      "$value": "#e6f9f9"
    },
    "mint-100": {
      "$extensions": {
        "com.figma.hiddenFromPublishing": false
      },
      "$type": "color",
      "$value": "#b0eeeb"
    },
    "mint-200": {
      "$extensions": {
        "com.figma.hiddenFromPublishing": false
      },
      "$type": "color",
      "$value": "#8ae5e1"
    },
    "mint-300": {
      "$extensions": {
        "com.figma.hiddenFromPublishing": false
      },
      "$type": "color",
      "$value": "#54d9d3"
    },
    "mint-400": {
      "$extensions": {
        "com.figma.hiddenFromPublishing": false
      },
      "$type": "color",
      "$value": "#33d2cb"
    },
    "mint-500": {
      "$extensions": {
        "com.figma.hiddenFromPublishing": false
      },
      "$type": "color",
      "$value": "#00c7be"
    },
    "mint-600": {
      "$extensions": {
        "com.figma.hiddenFromPublishing": false
      },
      "$type": "color",
      "$value": "#00b5ad"
    },
    "mint-700": {
      "$extensions": {
        "com.figma.hiddenFromPublishing": false
      },
      "$type": "color",
      "$value": "#008d87"
    },
    "mint-800": {
      "$extensions": {
        "com.figma.hiddenFromPublishing": false
      },
      "$type": "color",
      "$value": "#006d69"
    },
    "mint-900": {
      "$extensions": {
        "com.figma.hiddenFromPublishing": false
      },
      "$type": "color",
      "$value": "#005450"
    },
    "teal-50": {
      "$extensions": {
        "com.figma.hiddenFromPublishing": false
      },
      "$type": "color",
      "$value": "#eaf7f9"
    },
    "teal-100": {
      "$extensions": {
        "com.figma.hiddenFromPublishing": false
      },
      "$type": "color",
      "$value": "#bfe7ee"
    },
    "teal-200": {
      "$extensions": {
        "com.figma.hiddenFromPublishing": false
      },
      "$type": "color",
      "$value": "#a0dbe5"
    },
    "teal-300": {
      "$extensions": {
        "com.figma.hiddenFromPublishing": false
      },
      "$type": "color",
      "$value": "#74cad9"
    },
    "teal-400": {
      "$extensions": {
        "com.figma.hiddenFromPublishing": false
      },
      "$type": "color",
      "$value": "#59c0d2"
    },
    "teal-500": {
      "$extensions": {
        "com.figma.hiddenFromPublishing": false
      },
      "$type": "color",
      "$value": "#30b0c7"
    },
    "teal-600": {
      "$extensions": {
        "com.figma.hiddenFromPublishing": false
      },
      "$type": "color",
      "$value": "#2ca0b5"
    },
    "teal-700": {
      "$extensions": {
        "com.figma.hiddenFromPublishing": false
      },
      "$type": "color",
      "$value": "#227d8d"
    },
    "teal-800": {
      "$extensions": {
        "com.figma.hiddenFromPublishing": false
      },
      "$type": "color",
      "$value": "#1a616d"
    },
    "teal-900": {
      "$extensions": {
        "com.figma.hiddenFromPublishing": false
      },
      "$type": "color",
      "$value": "#144a54"
    },
    "cyan-50": {
      "$extensions": {
        "com.figma.hiddenFromPublishing": false
      },
      "$type": "color",
      "$value": "#ebf7fd"
    },
    "cyan-100": {
      "$extensions": {
        "com.figma.hiddenFromPublishing": false
      },
      "$type": "color",
      "$value": "#bfe6f7"
    },
    "cyan-200": {
      "$extensions": {
        "com.figma.hiddenFromPublishing": false
      },
      "$type": "color",
      "$value": "#a1d9f4"
    },
    "cyan-300": {
      "$extensions": {
        "com.figma.hiddenFromPublishing": false
      },
      "$type": "color",
      "$value": "#76c8ee"
    },
    "cyan-400": {
      "$extensions": {
        "com.figma.hiddenFromPublishing": false
      },
      "$type": "color",
      "$value": "#5bbdeb"
    },
    "cyan-500": {
      "$extensions": {
        "com.figma.hiddenFromPublishing": false
      },
      "$type": "color",
      "$value": "#32ade6"
    },
    "cyan-600": {
      "$extensions": {
        "com.figma.hiddenFromPublishing": false
      },
      "$type": "color",
      "$value": "#2e9dd1"
    },
    "cyan-700": {
      "$extensions": {
        "com.figma.hiddenFromPublishing": false
      },
      "$type": "color",
      "$value": "#247ba3"
    },
    "cyan-800": {
      "$extensions": {
        "com.figma.hiddenFromPublishing": false
      },
      "$type": "color",
      "$value": "#1c5f7f"
    },
    "cyan-900": {
      "$extensions": {
        "com.figma.hiddenFromPublishing": false
      },
      "$type": "color",
      "$value": "#154961"
    },
    "blue-50": {
      "$extensions": {
        "com.figma.hiddenFromPublishing": false
      },
      "$type": "color",
      "$value": "#e6f2ff"
    },
    "blue-100": {
      "$extensions": {
        "com.figma.hiddenFromPublishing": false
      },
      "$type": "color",
      "$value": "#b0d6ff"
    },
    "blue-200": {
      "$extensions": {
        "com.figma.hiddenFromPublishing": false
      },
      "$type": "color",
      "$value": "#8ac2ff"
    },
    "blue-300": {
      "$extensions": {
        "com.figma.hiddenFromPublishing": false
      },
      "$type": "color",
      "$value": "#54a6ff"
    },
    "blue-400": {
      "$extensions": {
        "com.figma.hiddenFromPublishing": false
      },
      "$type": "color",
      "$value": "#3395ff"
    },
    "blue-500": {
      "$extensions": {
        "com.figma.hiddenFromPublishing": false
      },
      "$type": "color",
      "$value": "#007aff"
    },
    "blue-600": {
      "$extensions": {
        "com.figma.hiddenFromPublishing": false
      },
      "$type": "color",
      "$value": "#006fe8"
    },
    "blue-700": {
      "$extensions": {
        "com.figma.hiddenFromPublishing": false
      },
      "$type": "color",
      "$value": "#0057b5"
    },
    "blue-800": {
      "$extensions": {
        "com.figma.hiddenFromPublishing": false
      },
      "$type": "color",
      "$value": "#00438c"
    },
    "blue-900": {
      "$extensions": {
        "com.figma.hiddenFromPublishing": false
      },
      "$type": "color",
      "$value": "#00336b"
    },
    "indigo-50": {
      "$extensions": {
        "com.figma.hiddenFromPublishing": false
      },
      "$type": "color",
      "$value": "#eeeefb"
    },
    "indigo-100": {
      "$extensions": {
        "com.figma.hiddenFromPublishing": false
      },
      "$type": "color",
      "$value": "#cbcbf2"
    },
    "indigo-200": {
      "$extensions": {
        "com.figma.hiddenFromPublishing": false
      },
      "$type": "color",
      "$value": "#b2b1ec"
    },
    "indigo-300": {
      "$extensions": {
        "com.figma.hiddenFromPublishing": false
      },
      "$type": "color",
      "$value": "#8f8ee4"
    },
    "indigo-400": {
      "$extensions": {
        "com.figma.hiddenFromPublishing": false
      },
      "$type": "color",
      "$value": "#7978de"
    },
    "indigo-500": {
      "$extensions": {
        "com.figma.hiddenFromPublishing": false
      },
      "$type": "color",
      "$value": "#5856d6"
    },
    "indigo-600": {
      "$extensions": {
        "com.figma.hiddenFromPublishing": false
      },
      "$type": "color",
      "$value": "#504ec3"
    },
    "indigo-700": {
      "$extensions": {
        "com.figma.hiddenFromPublishing": false
      },
      "$type": "color",
      "$value": "#3e3d98"
    },
    "indigo-800": {
      "$extensions": {
        "com.figma.hiddenFromPublishing": false
      },
      "$type": "color",
      "$value": "#302f76"
    },
    "indigo-900": {
      "$extensions": {
        "com.figma.hiddenFromPublishing": false
      },
      "$type": "color",
      "$value": "#25245a"
    },
    "purple-50": {
      "$extensions": {
        "com.figma.hiddenFromPublishing": false
      },
      "$type": "color",
      "$value": "#f7eefc"
    },
    "purple-100": {
      "$extensions": {
        "com.figma.hiddenFromPublishing": false
      },
      "$type": "color",
      "$value": "#e6c9f5"
    },
    "purple-200": {
      "$extensions": {
        "com.figma.hiddenFromPublishing": false
      },
      "$type": "color",
      "$value": "#daaff0"
    },
    "purple-300": {
      "$extensions": {
        "com.figma.hiddenFromPublishing": false
      },
      "$type": "color",
      "$value": "#c98be9"
    },
    "purple-400": {
      "$extensions": {
        "com.figma.hiddenFromPublishing": false
      },
      "$type": "color",
      "$value": "#bf75e5"
    },
    "purple-500": {
      "$extensions": {
        "com.figma.hiddenFromPublishing": false
      },
      "$type": "color",
      "$value": "#af52de"
    },
    "purple-600": {
      "$extensions": {
        "com.figma.hiddenFromPublishing": false
      },
      "$type": "color",
      "$value": "#9f4bca"
    },
    "purple-700": {
      "$extensions": {
        "com.figma.hiddenFromPublishing": false
      },
      "$type": "color",
      "$value": "#7c3a9e"
    },
    "purple-800": {
      "$extensions": {
        "com.figma.hiddenFromPublishing": false
      },
      "$type": "color",
      "$value": "#602d7a"
    },
    "purple-900": {
      "$extensions": {
        "com.figma.hiddenFromPublishing": false
      },
      "$type": "color",
      "$value": "#4a225d"
    }
  },
  "Size": {
    "1": {
      "$extensions": {
        "com.figma.hiddenFromPublishing": false
      },
      "$type": "number",
      "$value": 4
    },
    "2": {
      "$extensions": {
        "com.figma.hiddenFromPublishing": false
      },
      "$type": "number",
      "$value": 8
    },
    "3": {
      "$extensions": {
        "com.figma.hiddenFromPublishing": false
      },
      "$type": "number",
      "$value": 12
    },
    "4": {
      "$extensions": {
        "com.figma.hiddenFromPublishing": false
      },
      "$type": "number",
      "$value": 16
    },
    "5": {
      "$extensions": {
        "com.figma.hiddenFromPublishing": false
      },
      "$type": "number",
      "$value": 20
    },
    "6": {
      "$extensions": {
        "com.figma.hiddenFromPublishing": false
      },
      "$type": "number",
      "$value": 24
    },
    "7": {
      "$extensions": {
        "com.figma.hiddenFromPublishing": false
      },
      "$type": "number",
      "$value": 28
    },
    "8": {
      "$extensions": {
        "com.figma.hiddenFromPublishing": false
      },
      "$type": "number",
      "$value": 32
    },
    "9": {
      "$extensions": {
        "com.figma.hiddenFromPublishing": false
      },
      "$type": "number",
      "$value": 36
    },
    "10": {
      "$extensions": {
        "com.figma.hiddenFromPublishing": false
      },
      "$type": "number",
      "$value": 40
    },
    "11": {
      "$extensions": {
        "com.figma.hiddenFromPublishing": false
      },
      "$type": "number",
      "$value": 44
    },
    "12": {
      "$extensions": {
        "com.figma.hiddenFromPublishing": false
      },
      "$type": "number",
      "$value": 48
    },
    "14": {
      "$extensions": {
        "com.figma.hiddenFromPublishing": false
      },
      "$type": "number",
      "$value": 56
    },
    "16": {
      "$extensions": {
        "com.figma.hiddenFromPublishing": false
      },
      "$type": "number",
      "$value": 64
    },
    "20": {
      "$extensions": {
        "com.figma.hiddenFromPublishing": false
      },
      "$type": "number",
      "$value": 80
    },
    "24": {
      "$extensions": {
        "com.figma.hiddenFromPublishing": false
      },
      "$type": "number",
      "$value": 96
    },
    "28": {
      "$extensions": {
        "com.figma.hiddenFromPublishing": false
      },
      "$type": "number",
      "$value": 112
    },
    "32": {
      "$extensions": {
        "com.figma.hiddenFromPublishing": false
      },
      "$type": "number",
      "$value": 128
    },
    "40": {
      "$extensions": {
        "com.figma.hiddenFromPublishing": false
      },
      "$type": "number",
      "$value": 160
    },
    "48": {
      "$extensions": {
        "com.figma.hiddenFromPublishing": false
      },
      "$type": "number",
      "$value": 192
    },
    "56": {
      "$extensions": {
        "com.figma.hiddenFromPublishing": false
      },
      "$type": "number",
      "$value": 224
    },
    "64": {
      "$extensions": {
        "com.figma.hiddenFromPublishing": false
      },
      "$type": "number",
      "$value": 256
    },
    "2half": {
      "$extensions": {
        "com.figma.hiddenFromPublishing": false
      },
      "$type": "number",
      "$value": 10
    },
    "1half": {
      "$extensions": {
        "com.figma.hiddenFromPublishing": false
      },
      "$type": "number",
      "$value": 6
    },
    "half": {
      "$extensions": {
        "com.figma.hiddenFromPublishing": false
      },
      "$type": "number",
      "$value": 2
    }
  }
}
